{"moduleName":null,"summaries":[{"symbol":{"__symbol":0,"members":[]},"metadata":"https://ngrx.io/guide/store/configuration/runtime-checks"},{"symbol":{"__symbol":1,"members":[]},"metadata":{"__symbolic":"function","parameters":["target"],"value":{"__symbolic":"binop","operator":"===","left":{"__symbolic":"reference","name":"target"}}}},{"symbol":{"__symbol":2,"members":[]},"metadata":{"__symbolic":"function","parameters":["target"],"value":{"__symbolic":"binop","operator":"===","left":{"__symbolic":"reference","name":"target"},"right":null}}},{"symbol":{"__symbol":3,"members":[]},"metadata":{"__symbolic":"function","parameters":["target"],"value":{"__symbolic":"call","expression":{"__symbolic":"select","member":"isArray"},"arguments":[{"__symbolic":"reference","name":"target"}]}}},{"symbol":{"__symbol":4,"members":[]},"metadata":{"__symbolic":"function","parameters":["target"],"value":{"__symbolic":"binop","operator":"===","left":{"__symbolic":"error","message":"Expression form not supported","fileName":"modules/store/src/meta-reducers/utils.ts"},"right":"string"}}},{"symbol":{"__symbol":5,"members":[]},"metadata":{"__symbolic":"function","parameters":["target"],"value":{"__symbolic":"binop","operator":"===","left":{"__symbolic":"error","message":"Expression form not supported","fileName":"modules/store/src/meta-reducers/utils.ts"},"right":"boolean"}}},{"symbol":{"__symbol":6,"members":[]},"metadata":{"__symbolic":"function","parameters":["target"],"value":{"__symbolic":"binop","operator":"===","left":{"__symbolic":"error","message":"Expression form not supported","fileName":"modules/store/src/meta-reducers/utils.ts"},"right":"number"}}},{"symbol":{"__symbol":7,"members":[]},"metadata":{"__symbolic":"function","parameters":["target"],"value":{"__symbolic":"binop","operator":"&&","left":{"__symbolic":"binop","operator":"===","left":{"__symbolic":"error","message":"Expression form not supported","fileName":"modules/store/src/meta-reducers/utils.ts"},"right":"object"},"right":{"__symbolic":"binop","operator":"!==","left":{"__symbolic":"reference","name":"target"},"right":null}}}},{"symbol":{"__symbol":8,"members":[]},"metadata":{"__symbolic":"function","parameters":["target"],"value":{"__symbolic":"binop","operator":"&&","left":{"__symbolic":"call","expression":{"__symbol":7,"members":[]},"arguments":[{"__symbolic":"reference","name":"target"}]},"right":{"__symbolic":"pre","operator":"!","operand":{"__symbolic":"call","expression":{"__symbol":3,"members":[]},"arguments":[{"__symbolic":"reference","name":"target"}]}}}}},{"symbol":{"__symbol":9,"members":[]},"metadata":{"__symbolic":"function"}},{"symbol":{"__symbol":10,"members":[]},"metadata":{"__symbolic":"function","parameters":["target"],"value":{"__symbolic":"binop","operator":"===","left":{"__symbolic":"error","message":"Expression form not supported","fileName":"modules/store/src/meta-reducers/utils.ts"},"right":"function"}}},{"symbol":{"__symbol":11,"members":[]},"metadata":{"__symbolic":"function","parameters":["target"],"value":{"__symbolic":"binop","operator":"&&","left":{"__symbolic":"call","expression":{"__symbol":10,"members":[]},"arguments":[{"__symbolic":"reference","name":"target"}]},"right":{"__symbolic":"call","expression":{"__symbolic":"select","expression":{"__symbolic":"reference","name":"target"},"member":"hasOwnProperty"},"arguments":["ɵcmp"]}}}},{"symbol":{"__symbol":12,"members":[]},"metadata":{"__symbolic":"function","parameters":["target","propertyName"],"value":{"__symbolic":"call","expression":{"__symbolic":"select","expression":{"__symbolic":"select","expression":{"__symbolic":"select","member":"prototype"},"member":"hasOwnProperty"},"member":"call"},"arguments":[{"__symbolic":"reference","name":"target"},{"__symbolic":"reference","name":"propertyName"}]}}}],"symbols":[{"__symbol":0,"name":"RUNTIME_CHECK_URL","filePath":"./utils"},{"__symbol":1,"name":"isUndefined","filePath":"./utils"},{"__symbol":2,"name":"isNull","filePath":"./utils"},{"__symbol":3,"name":"isArray","filePath":"./utils"},{"__symbol":4,"name":"isString","filePath":"./utils"},{"__symbol":5,"name":"isBoolean","filePath":"./utils"},{"__symbol":6,"name":"isNumber","filePath":"./utils"},{"__symbol":7,"name":"isObjectLike","filePath":"./utils"},{"__symbol":8,"name":"isObject","filePath":"./utils"},{"__symbol":9,"name":"isPlainObject","filePath":"./utils"},{"__symbol":10,"name":"isFunction","filePath":"./utils"},{"__symbol":11,"name":"isComponent","filePath":"./utils"},{"__symbol":12,"name":"hasOwnProperty","filePath":"./utils"}]}